Metadata-Version: 2.1
Name: no2foryou
Version: 3.0.0
Summary: Replaces your Python 2 commands with error messages
Home-page: https://github.com/nvllsvm/python-no2foryou
Author: Andrew Rabert
Author-email: ar@nullsum.net
License: WTFPL
Platform: UNKNOWN
Requires-Python: >=3.6
